{
    "positions": [
        {
            "analyses": [],
            "decay_constants": {
                "lambda_k_total": 5.5428e-10,
                "lambda_k_total_error": 0.0
            },
            "identifier": "2796",
            "j": 0.013960734634117199,
            "j_err": 8.914186626620785e-06,
            "mean_j": 0.0,
            "mean_j_err": 0.0,
            "mean_j_mswd": 0.0,
            "options": {
                "model_kind": "Plane",
                "monitor_age": 28.201,
                "monitor_material": "",
                "monitor_name": "",
                "monitor_reference": "FC SJ",
                "monte_carlo_ntrials": 10,
                "predicted_j_error_type": "SEM, but if MSWD>1 use SEM * sqrt(MSWD)",
                "use_monte_carlo": false,
                "use_weighted_fit": false
            },
            "position": 1,
            "position_jerr": 0.0
        },
        {
            "analyses": [],
            "decay_constants": {
                "lambda_k_total": 5.5428e-10,
                "lambda_k_total_error": 0.0
            },
            "identifier": "2797",
            "j": 0.013960734634117199,
            "j_err": 8.914186626620785e-06,
            "mean_j": 0.0,
            "mean_j_err": 0.0,
            "mean_j_mswd": 0.0,
            "options": {
                "model_kind": "Plane",
                "monitor_age": 28.201,
                "monitor_material": "",
                "monitor_name": "",
                "monitor_reference": "FC SJ",
                "monte_carlo_ntrials": 10,
                "predicted_j_error_type": "SEM, but if MSWD>1 use SEM * sqrt(MSWD)",
                "use_monte_carlo": false,
                "use_weighted_fit": false
            },
            "position": 2,
            "position_jerr": 0.0
        },
        {
            "analyses": [],
            "decay_constants": {
                "lambda_k_total": 5.5428e-10,
                "lambda_k_total_error": 0.0
            },
            "identifier": "2798",
            "j": 0.01396831309892628,
            "j_err": 8.913805477917534e-06,
            "mean_j": 0.0,
            "mean_j_err": 0.0,
            "mean_j_mswd": 0.0,
            "options": {
                "model_kind": "Plane",
                "monitor_age": 28.201,
                "monitor_material": "",
                "monitor_name": "",
                "monitor_reference": "FC SJ",
                "monte_carlo_ntrials": 10,
                "predicted_j_error_type": "SEM, but if MSWD>1 use SEM * sqrt(MSWD)",
                "use_monte_carlo": false,
                "use_weighted_fit": false
            },
            "position": 3,
            "position_jerr": 0.0
        },
        {
            "analyses": [],
            "decay_constants": {
                "lambda_k_total": 5.5428e-10,
                "lambda_k_total_error": 0.0
            },
            "identifier": "2799",
            "j": 0.01396831309892628,
            "j_err": 8.913805477917534e-06,
            "mean_j": 0.0,
            "mean_j_err": 0.0,
            "mean_j_mswd": 0.0,
            "options": {
                "model_kind": "Plane",
                "monitor_age": 28.201,
                "monitor_material": "",
                "monitor_name": "",
                "monitor_reference": "FC SJ",
                "monte_carlo_ntrials": 10,
                "predicted_j_error_type": "SEM, but if MSWD>1 use SEM * sqrt(MSWD)",
                "use_monte_carlo": false,
                "use_weighted_fit": false
            },
            "position": 4,
            "position_jerr": 0.0
        },
        {
            "analyses": [],
            "decay_constants": {
                "lambda_k_total": 5.5428e-10,
                "lambda_k_total_error": 0.0
            },
            "identifier": "2800",
            "j": 0.013978774493378475,
            "j_err": 8.922148145737218e-06,
            "mean_j": 0.0,
            "mean_j_err": 0.0,
            "mean_j_mswd": 0.0,
            "options": {
                "model_kind": "Plane",
                "monitor_age": 28.201,
                "monitor_material": "",
                "monitor_name": "",
                "monitor_reference": "FC SJ",
                "monte_carlo_ntrials": 10,
                "predicted_j_error_type": "SEM, but if MSWD>1 use SEM * sqrt(MSWD)",
                "use_monte_carlo": false,
                "use_weighted_fit": false
            },
            "position": 5,
            "position_jerr": 0.0
        },
        {
            "analyses": [],
            "decay_constants": {
                "lambda_k_total": 5.5428e-10,
                "lambda_k_total_error": 0.0
            },
            "identifier": "2801",
            "j": 0.013978774493378475,
            "j_err": 8.922148145737218e-06,
            "mean_j": 0.0,
            "mean_j_err": 0.0,
            "mean_j_mswd": 0.0,
            "options": {
                "model_kind": "Plane",
                "monitor_age": 28.201,
                "monitor_material": "",
                "monitor_name": "",
                "monitor_reference": "FC SJ",
                "monte_carlo_ntrials": 10,
                "predicted_j_error_type": "SEM, but if MSWD>1 use SEM * sqrt(MSWD)",
                "use_monte_carlo": false,
                "use_weighted_fit": false
            },
            "position": 6,
            "position_jerr": 0.0
        },
        {
            "analyses": [],
            "decay_constants": {
                "lambda_k_total": 5.5428e-10,
                "lambda_k_total_error": 0.0
            },
            "identifier": "2802",
            "j": 0.013977652019126272,
            "j_err": 8.922148145737218e-06,
            "mean_j": 0.0,
            "mean_j_err": 0.0,
            "mean_j_mswd": 0.0,
            "options": {
                "model_kind": "Plane",
                "monitor_age": 28.201,
                "monitor_material": "",
                "monitor_name": "",
                "monitor_reference": "FC SJ",
                "monte_carlo_ntrials": 10,
                "predicted_j_error_type": "SEM, but if MSWD>1 use SEM * sqrt(MSWD)",
                "use_monte_carlo": false,
                "use_weighted_fit": false
            },
            "position": 7,
            "position_jerr": 0.0
        },
        {
            "analyses": [],
            "decay_constants": {
                "lambda_k_total": 5.5428e-10,
                "lambda_k_total_error": 0.0
            },
            "identifier": "2803",
            "j": 0.013977652019126272,
            "j_err": 8.922148145737218e-06,
            "mean_j": 0.0,
            "mean_j_err": 0.0,
            "mean_j_mswd": 0.0,
            "options": {
                "model_kind": "Plane",
                "monitor_age": 28.201,
                "monitor_material": "",
                "monitor_name": "",
                "monitor_reference": "FC SJ",
                "monte_carlo_ntrials": 10,
                "predicted_j_error_type": "SEM, but if MSWD>1 use SEM * sqrt(MSWD)",
                "use_monte_carlo": false,
                "use_weighted_fit": false
            },
            "position": 8,
            "position_jerr": 0.0
        },
        {
            "analyses": [],
            "decay_constants": {
                "lambda_k_total": 5.5428e-10,
                "lambda_k_total_error": 0.0
            },
            "identifier": "2804",
            "j": 0.013966502014583188,
            "j_err": 8.913805477917535e-06,
            "mean_j": 0.0,
            "mean_j_err": 0.0,
            "mean_j_mswd": 0.0,
            "options": {
                "model_kind": "Plane",
                "monitor_age": 28.201,
                "monitor_material": "",
                "monitor_name": "",
                "monitor_reference": "FC SJ",
                "monte_carlo_ntrials": 10,
                "predicted_j_error_type": "SEM, but if MSWD>1 use SEM * sqrt(MSWD)",
                "use_monte_carlo": false,
                "use_weighted_fit": false
            },
            "position": 9,
            "position_jerr": 0.0
        },
        {
            "analyses": [],
            "decay_constants": {
                "lambda_k_total": 5.5428e-10,
                "lambda_k_total_error": 0.0
            },
            "identifier": "2805",
            "j": 0.013966502014583188,
            "j_err": 8.913805477917535e-06,
            "mean_j": 0.0,
            "mean_j_err": 0.0,
            "mean_j_mswd": 0.0,
            "options": {
                "model_kind": "Plane",
                "monitor_age": 28.201,
                "monitor_material": "",
                "monitor_name": "",
                "monitor_reference": "FC SJ",
                "monte_carlo_ntrials": 10,
                "predicted_j_error_type": "SEM, but if MSWD>1 use SEM * sqrt(MSWD)",
                "use_monte_carlo": false,
                "use_weighted_fit": false
            },
            "position": 10,
            "position_jerr": 0.0
        },
        {
            "analyses": [
                {
                    "is_omitted": false,
                    "record_id": "2806-01A",
                    "uuid": "1ae46b38-e909-456a-b8bd-766ad5174968"
                }
            ],
            "decay_constants": {
                "lambda_k_total": 5.5428e-10,
                "lambda_k_total_error": 0.0
            },
            "identifier": "2806",
            "j": 0.013959312353979536,
            "j_err": 1.1543338150227023e-05,
            "mean_j": 0.013952629617178192,
            "mean_j_err": 0.0,
            "mean_j_mswd": 0.0,
            "options": {
                "model_kind": "Plane",
                "monitor_age": 28.201,
                "monitor_material": "",
                "monitor_name": "",
                "monitor_reference": "FC SJ",
                "monte_carlo_ntrials": 10,
                "predicted_j_error_type": "SEM, but if MSWD>1 use SEM * sqrt(MSWD)",
                "use_monte_carlo": false,
                "use_weighted_fit": false
            },
            "position": 11,
            "position_jerr": 0.0
        },
        {
            "analyses": [
                {
                    "is_omitted": false,
                    "record_id": "2807-01A",
                    "uuid": "f325a489-d2e9-4936-acc8-a29d3c1d18da"
                }
            ],
            "decay_constants": {
                "lambda_k_total": 5.5428e-10,
                "lambda_k_total_error": 0.0
            },
            "identifier": "2807",
            "j": 0.013976330545328038,
            "j_err": 1.1538915557216914e-05,
            "mean_j": 0.01397238520273518,
            "mean_j_err": 0.0,
            "mean_j_mswd": 0.0,
            "options": {
                "model_kind": "Plane",
                "monitor_age": 28.201,
                "monitor_material": "",
                "monitor_name": "",
                "monitor_reference": "FC SJ",
                "monte_carlo_ntrials": 10,
                "predicted_j_error_type": "SEM, but if MSWD>1 use SEM * sqrt(MSWD)",
                "use_monte_carlo": false,
                "use_weighted_fit": false
            },
            "position": 12,
            "position_jerr": 0.0
        },
        {
            "analyses": [
                {
                    "is_omitted": false,
                    "record_id": "2808-01A",
                    "uuid": "05b7bc49-83ff-47b3-964c-c1faa224b29a"
                }
            ],
            "decay_constants": {
                "lambda_k_total": 5.5428e-10,
                "lambda_k_total_error": 0.0
            },
            "identifier": "2808",
            "j": 0.0139851482574225,
            "j_err": 1.1543621692359259e-05,
            "mean_j": 0.013997679612834277,
            "mean_j_err": 0.0,
            "mean_j_mswd": 0.0,
            "options": {
                "model_kind": "Plane",
                "monitor_age": 28.201,
                "monitor_material": "",
                "monitor_name": "",
                "monitor_reference": "FC SJ",
                "monte_carlo_ntrials": 10,
                "predicted_j_error_type": "SEM, but if MSWD>1 use SEM * sqrt(MSWD)",
                "use_monte_carlo": false,
                "use_weighted_fit": false
            },
            "position": 13,
            "position_jerr": 0.0
        },
        {
            "analyses": [
                {
                    "is_omitted": false,
                    "record_id": "2809-01A",
                    "uuid": "de0c95ad-c0ef-452a-9cc8-ddc6e24173f0"
                }
            ],
            "decay_constants": {
                "lambda_k_total": 5.5428e-10,
                "lambda_k_total_error": 0.0
            },
            "identifier": "2809",
            "j": 0.01397356416374903,
            "j_err": 1.1538915557216914e-05,
            "mean_j": 0.013956682114767595,
            "mean_j_err": 0.0,
            "mean_j_mswd": 0.0,
            "options": {
                "model_kind": "Plane",
                "monitor_age": 28.201,
                "monitor_material": "",
                "monitor_name": "",
                "monitor_reference": "FC SJ",
                "monte_carlo_ntrials": 10,
                "predicted_j_error_type": "SEM, but if MSWD>1 use SEM * sqrt(MSWD)",
                "use_monte_carlo": false,
                "use_weighted_fit": false
            },
            "position": 14,
            "position_jerr": 0.0
        },
        {
            "analyses": [
                {
                    "is_omitted": false,
                    "record_id": "2810-01A",
                    "uuid": "92d29bdb-73ef-4426-8f44-9aea4ba25523"
                }
            ],
            "decay_constants": {
                "lambda_k_total": 5.5428e-10,
                "lambda_k_total_error": 0.0
            },
            "identifier": "2810",
            "j": 0.013957600779765185,
            "j_err": 1.1543338150227027e-05,
            "mean_j": 0.013971827370731417,
            "mean_j_err": 0.0,
            "mean_j_mswd": 0.0,
            "options": {
                "model_kind": "Plane",
                "monitor_age": 28.201,
                "monitor_material": "",
                "monitor_name": "",
                "monitor_reference": "FC SJ",
                "monte_carlo_ntrials": 10,
                "predicted_j_error_type": "SEM, but if MSWD>1 use SEM * sqrt(MSWD)",
                "use_monte_carlo": false,
                "use_weighted_fit": false
            },
            "position": 15,
            "position_jerr": 0.0
        },
        {
            "analyses": [
                {
                    "is_omitted": false,
                    "record_id": "2811-01A",
                    "uuid": "1ee81d11-bd45-4fa4-be4c-d24237c70877"
                }
            ],
            "decay_constants": {
                "lambda_k_total": 5.5428e-10,
                "lambda_k_total_error": 0.0
            },
            "identifier": "2811",
            "j": 0.013970391220048858,
            "j_err": 6.2593255488508356e-06,
            "mean_j": 0.013971143402046448,
            "mean_j_err": 0.0,
            "mean_j_mswd": 0.0,
            "options": {
                "model_kind": "Plane",
                "monitor_age": 28.201,
                "monitor_material": "",
                "monitor_name": "",
                "monitor_reference": "FC SJ",
                "monte_carlo_ntrials": 10,
                "predicted_j_error_type": "SEM, but if MSWD>1 use SEM * sqrt(MSWD)",
                "use_monte_carlo": false,
                "use_weighted_fit": false
            },
            "position": 16,
            "position_jerr": 0.0
        }
    ],
    "z": 0.0
}