{
    "positions": [
        {
            "analyses": [],
            "decay_constants": {
                "lambda_k_total": 5.5428e-10,
                "lambda_k_total_error": 0.0
            },
            "identifier": "3818",
            "j": 0.00938656601719081,
            "j_err": 3.028386173902723e-06,
            "mean_j": 0.0,
            "mean_j_err": 0.0,
            "mean_j_mswd": 0.0,
            "options": {
                "interpolation_style": "Weighted Mean",
                "model_kind": "Plane",
                "monitor_age": 28.201,
                "monitor_material": "",
                "monitor_name": "",
                "monitor_reference": "FC SJ",
                "monte_carlo_ntrials": 10,
                "predicted_j_error_type": "SE but if MSWD>1 use SE * sqrt(MSWD)",
                "use_monte_carlo": false,
                "use_weighted_fit": false
            },
            "position": 1,
            "position_jerr": 0.0
        },
        {
            "analyses": [],
            "decay_constants": {
                "lambda_k_total": 5.5428e-10,
                "lambda_k_total_error": 0.0
            },
            "identifier": "3819",
            "j": 0.00938656601719081,
            "j_err": 3.028386173902723e-06,
            "mean_j": 0.0,
            "mean_j_err": 0.0,
            "mean_j_mswd": 0.0,
            "options": {
                "interpolation_style": "Weighted Mean",
                "model_kind": "Plane",
                "monitor_age": 28.201,
                "monitor_material": "",
                "monitor_name": "",
                "monitor_reference": "FC SJ",
                "monte_carlo_ntrials": 10,
                "predicted_j_error_type": "SE but if MSWD>1 use SE * sqrt(MSWD)",
                "use_monte_carlo": false,
                "use_weighted_fit": false
            },
            "position": 2,
            "position_jerr": 0.0
        },
        {
            "analyses": [],
            "decay_constants": {
                "lambda_k_total": 5.5428e-10,
                "lambda_k_total_error": 0.0
            },
            "identifier": "3820",
            "j": 0.00938656601719081,
            "j_err": 3.028386173902723e-06,
            "mean_j": 0.0,
            "mean_j_err": 0.0,
            "mean_j_mswd": 0.0,
            "options": {
                "interpolation_style": "Weighted Mean",
                "model_kind": "Plane",
                "monitor_age": 28.201,
                "monitor_material": "",
                "monitor_name": "",
                "monitor_reference": "FC SJ",
                "monte_carlo_ntrials": 10,
                "predicted_j_error_type": "SE but if MSWD>1 use SE * sqrt(MSWD)",
                "use_monte_carlo": false,
                "use_weighted_fit": false
            },
            "position": 3,
            "position_jerr": 0.0
        },
        {
            "analyses": [],
            "decay_constants": {
                "lambda_k_total": 5.5428e-10,
                "lambda_k_total_error": 0.0
            },
            "identifier": "3821",
            "j": 0.00938656601719081,
            "j_err": 3.028386173902723e-06,
            "mean_j": 0.0,
            "mean_j_err": 0.0,
            "mean_j_mswd": 0.0,
            "options": {
                "interpolation_style": "Weighted Mean",
                "model_kind": "Plane",
                "monitor_age": 28.201,
                "monitor_material": "",
                "monitor_name": "",
                "monitor_reference": "FC SJ",
                "monte_carlo_ntrials": 10,
                "predicted_j_error_type": "SE but if MSWD>1 use SE * sqrt(MSWD)",
                "use_monte_carlo": false,
                "use_weighted_fit": false
            },
            "position": 4,
            "position_jerr": 0.0
        },
        {
            "analyses": [
                {
                    "is_omitted": false,
                    "record_id": "3822-01A",
                    "uuid": "f8725cdc-e315-4df5-8969-dba38b84d759"
                }
            ],
            "decay_constants": {
                "lambda_k_total": 5.5428e-10,
                "lambda_k_total_error": 0.0
            },
            "identifier": "3822",
            "j": 0.009377623169431939,
            "j_err": 5.245318718138633e-06,
            "mean_j": 0.009380651555605841,
            "mean_j_err": 0.0,
            "mean_j_mswd": 0.0,
            "options": {
                "interpolation_style": "Weighted Mean",
                "model_kind": "Plane",
                "monitor_age": 28.201,
                "monitor_material": "",
                "monitor_name": "",
                "monitor_reference": "FC SJ",
                "monte_carlo_ntrials": 10,
                "predicted_j_error_type": "SE but if MSWD>1 use SE * sqrt(MSWD)",
                "use_monte_carlo": false,
                "use_weighted_fit": false
            },
            "position": 5,
            "position_jerr": 0.0
        },
        {
            "analyses": [
                {
                    "is_omitted": false,
                    "record_id": "3823-01A",
                    "uuid": "ead9876f-c9d2-4418-8be4-423655d3e600"
                }
            ],
            "decay_constants": {
                "lambda_k_total": 5.5428e-10,
                "lambda_k_total_error": 0.0
            },
            "identifier": "3823",
            "j": 0.009375407378278485,
            "j_err": 5.245318718138633e-06,
            "mean_j": 0.009372378992104583,
            "mean_j_err": 0.0,
            "mean_j_mswd": 0.0,
            "options": {
                "interpolation_style": "Weighted Mean",
                "model_kind": "Plane",
                "monitor_age": 28.201,
                "monitor_material": "",
                "monitor_name": "",
                "monitor_reference": "FC SJ",
                "monte_carlo_ntrials": 10,
                "predicted_j_error_type": "SE but if MSWD>1 use SE * sqrt(MSWD)",
                "use_monte_carlo": false,
                "use_weighted_fit": false
            },
            "position": 6,
            "position_jerr": 0.0
        },
        {
            "analyses": [
                {
                    "is_omitted": false,
                    "record_id": "3824-01A",
                    "uuid": "b86bdcf8-266e-42ac-bdc6-db4dec269a33"
                }
            ],
            "decay_constants": {
                "lambda_k_total": 5.5428e-10,
                "lambda_k_total_error": 0.0
            },
            "identifier": "3824",
            "j": 0.009395508864949682,
            "j_err": 5.245318718138634e-06,
            "mean_j": 0.009398537251123586,
            "mean_j_err": 0.0,
            "mean_j_mswd": 0.0,
            "options": {
                "interpolation_style": "Weighted Mean",
                "model_kind": "Plane",
                "monitor_age": 28.201,
                "monitor_material": "",
                "monitor_name": "",
                "monitor_reference": "FC SJ",
                "monte_carlo_ntrials": 10,
                "predicted_j_error_type": "SE but if MSWD>1 use SE * sqrt(MSWD)",
                "use_monte_carlo": false,
                "use_weighted_fit": false
            },
            "position": 7,
            "position_jerr": 0.0
        },
        {
            "analyses": [
                {
                    "is_omitted": false,
                    "record_id": "3825-01A",
                    "uuid": "54a8fd3f-b757-4be1-869b-50fed38ef099"
                }
            ],
            "decay_constants": {
                "lambda_k_total": 5.5428e-10,
                "lambda_k_total_error": 0.0
            },
            "identifier": "3825",
            "j": 0.009397724656103135,
            "j_err": 5.245318718138634e-06,
            "mean_j": 0.009394696269929233,
            "mean_j_err": 0.0,
            "mean_j_mswd": 0.0,
            "options": {
                "interpolation_style": "Weighted Mean",
                "model_kind": "Plane",
                "monitor_age": 28.201,
                "monitor_material": "",
                "monitor_name": "",
                "monitor_reference": "FC SJ",
                "monte_carlo_ntrials": 10,
                "predicted_j_error_type": "SE but if MSWD>1 use SE * sqrt(MSWD)",
                "use_monte_carlo": false,
                "use_weighted_fit": false
            },
            "position": 8,
            "position_jerr": 0.0
        }
    ],
    "z": 0
}